macromol_dataframe/__init__.py
macromol_dataframe/atoms.py
macromol_dataframe/coords.py
macromol_dataframe/error.py
macromol_dataframe/mmcif.py
macromol_dataframe/pymol.py
macromol_dataframe/residues.py
macromol_dataframe/testing.py
macromol_dataframe-0.9.0.dist-info/licenses/LICENSE.txt
macromol_dataframe-0.9.0.dist-info/WHEEL
macromol_dataframe-0.9.0.dist-info/METADATA
macromol_dataframe-0.9.0.dist-info/RECORD
