Metadata-Version: 2.4
Name: macromol_dataframe
Version: 0.9.0
Summary: Manipulate macromolecular coordinate data using data frames.
Author-email: Kale Kundert <kale@thekunderts.net>
Requires-Python: ~=3.8
Classifier: Programming Language :: Python :: 3
License-File: LICENSE.txt
Requires-Dist: gemmi
Requires-Dist: more_itertools
Requires-Dist: numpy
Requires-Dist: parsy
Requires-Dist: polars>=1.0
Requires-Dist: scipy
Requires-Dist: typing-extensions
Requires-Dist: sphinx ; extra == "doc"
Requires-Dist: sphinx_rtd_theme ; extra == "doc"
Requires-Dist: autoclasstoc ; extra == "doc"
Requires-Dist: pytest ; extra == "test"
Requires-Dist: parametrize_from_file ; extra == "test"
Requires-Dist: hypothesis ; extra == "test"
Project-URL: Bug Tracker, https://github.com/kalekundert/macromol_dataframe/issues
Project-URL: Continuous Integration, https://github.com/kalekundert/macromol_dataframe/actions
Project-URL: Documentation, https://macromol-dataframe.readthedocs.io/en/latest/
Project-URL: Test Coverage, https://coveralls.io/github/kalekundert/macromol_dataframe
Project-URL: Version Control, https://github.com/kalekundert/macromol_dataframe
Provides-Extra: doc
Provides-Extra: test
